typographeur/__init__.py
typographeur/ligatures.py
typographeur-0.5.0.dist-info/METADATA
typographeur-0.5.0.dist-info/RECORD
typographeur-0.5.0.dist-info/WHEEL
typographeur-0.5.0.dist-info/entry_points.txt
typographeur-0.5.0.dist-info/top_level.txt
typographeur-0.5.0.dist-info/zip-safe
