Metadata-Version: 2.1
Name: typographeur
Version: 0.5.0
Summary: Faire respecter les règles typographiques françaises en HTML.
Home-page: https://github.com/brunobord/typographeur/
Author: Bruno Bord
Author-email: bruno@jehaisleprintemps.net
License: MIT
Keywords: text processing typography
Platform: UNKNOWN
Classifier: Development Status :: 4 - Beta
Classifier: License :: OSI Approved :: MIT License
Classifier: Operating System :: OS Independent
Classifier: Natural Language :: French
Classifier: Programming Language :: Python :: 3
Classifier: Programming Language :: Python :: 3.6
Classifier: Programming Language :: Python :: 3.7
Classifier: Programming Language :: Python :: 3.8
Classifier: Topic :: Text Processing :: Filters
Classifier: Topic :: Text Processing :: Markup :: HTML
Provides-Extra: dev
Provides-Extra: test
Provides-Extra: dev
Provides-Extra: test
Requires-Dist: pytest; extra == 'test'
Requires-Dist: flake8; extra == 'test'
